{
  "imports": {
    "std/": "https://deno.land/std@0.186.0/",
    "cliffy/": "https://deno.land/x/cliffy@v0.25.7/",
    "@digitalbazaar/ed25519-signature-2020": "https://cdn.skypack.dev/@digitalbazaar/ed25519-signature-2020@5.2.0?dts",
    "@digitalbazaar/ed25519-verification-key-2020": "https://cdn.skypack.dev/@digitalbazaar/ed25519-verification-key-2020@4.1.0?dts",
    "@digitalbazaar/vc": "https://cdn.skypack.dev/@digitalbazaar/vc@6.0.1?dts",
    "@digitalbazaar/x25519-key-agreement-key-2020": "https://cdn.skypack.dev/@digitalbazaar/x25519-key-agreement-key-2020@3.0.1?dts",
    "crypto-ld": "https://cdn.skypack.dev/crypto-ld@7.0.0?dts",
    "did-resolver": "https://cdn.skypack.dev/did-resolver@4.0.1?dts",
    "doctest": "https://cdn.skypack.dev/doctest@0.19.0?dts",
    "fluture-sanctuary-types": "https://cdn.skypack.dev/fluture-sanctuary-types@7.1.0?dts",
    "fluture": "https://cdn.skypack.dev/fluture@14.0.0?dts",
    "jsonld-signatures": "https://cdn.skypack.dev/jsonld-signatures@11.1.0?dts",
    "sanctuary-def": "https://cdn.skypack.dev/sanctuary-def@0.22.0?dts",
    "sanctuary": "https://cdn.skypack.dev/sanctuary@3.1.0?dts",
    "web-did-resolver": "https://cdn.skypack.dev/web-did-resolver@2.0.21?dts"
  },
  "scopes": {
    "https://cdn.skypack.dev/": {
      "@noble/ed25519": "https://cdn.skypack.dev/@noble/ed25519@1.7.3?dts",
      "acorn": "https://cdn.skypack.dev/acorn@8.5.0?dts",
      "base58-universal": "https://cdn.skypack.dev/base58-universal@2.0.0?dts",
      "base64url-universal": "https://cdn.skypack.dev/base64url-universal@2.0.0?dts",
      "bindings": "https://cdn.skypack.dev/bindings@1.5.0?dts",
      "coffeescript": "https://cdn.skypack.dev/coffeescript@1.12.7?dts",
      "commander": "https://cdn.skypack.dev/commander@2.20.3?dts",
      "credentials-context": "https://cdn.skypack.dev/credentials-context@2.0.0?dts",
      "cross-fetch": "https://cdn.skypack.dev/cross-fetch@3.1.5?dts",
      "ed25519-signature-2018-context": "https://cdn.skypack.dev/ed25519-signature-2018-context@1.1.0?dts",
      "ed25519-signature-2020-context": "https://cdn.skypack.dev/ed25519-signature-2020-context@1.1.0?dts",
      "jsonld": "https://cdn.skypack.dev/jsonld@8.1.1?dts",
      "nan": "https://cdn.skypack.dev/nan@2.17.0?dts",
      "sanctuary-either": "https://cdn.skypack.dev/sanctuary-either@2.1.0?dts",
      "sanctuary-maybe": "https://cdn.skypack.dev/sanctuary-maybe@2.1.0?dts",
      "sanctuary-pair": "https://cdn.skypack.dev/sanctuary-pair@2.1.0?dts",
      "sanctuary-show": "https://cdn.skypack.dev/sanctuary-show@2.0.0?dts",
      "sanctuary-type-classes": "https://cdn.skypack.dev/sanctuary-type-classes@12.1.0?dts",
      "sanctuary-type-identifiers": "https://cdn.skypack.dev/sanctuary-type-identifiers@3.0.0?dts",
      "security-context": "https://cdn.skypack.dev/security-context@4.0.0?dts",
      "serialize-error": "https://cdn.skypack.dev/serialize-error@8.1.0?dts",
      "setimmediate": "https://cdn.skypack.dev/setimmediate@1.0.5?dts",
      "tweetnacl": "https://cdn.skypack.dev/tweetnacl@1.0.3?dts"
    }
  }
}
